{
  "students": [
    {
      "fname": "Malkesh",
      "lname": "Dalia",
      "birthday": "29/11/1991",
      "gender": "male",
      "email": "malkesh2911@hotmail.com",
      "phone": "08980247057",
      "address": "4/468 Ghanchi Street, Begampura,",
      "id": 1
    },
    {
      "fname": "Malkesh",
      "lname": "Dalia",
      "birthday": "29/11/1991",
      "gender": "male",
      "email": "malkesh2911@hotmail.com",
      "phone": "08980247057",
      "address": "4/468 Ghanchi Street, Begampura,",
      "id": 2
    },
    {
      "fname": "Malkesh",
      "lname": "Dalia",
      "birthday": "29/11/1991",
      "gender": "male",
      "email": "malkesh2911@hotmail.com",
      "phone": "08980247057",
      "address": "4/468 Ghanchi Street, Begampura,",
      "id": 4
    },
    {
      "fname": "Nadeem Dalia",
      "lname": "Dalia",
      "email": "malkesh2911@hotmail.com",
      "phone": "08980247057",
      "address": "4/468 Ghanchi Street, Begampura,",
      "birthday": "29/11/1991",
      "gender": "male",
      "id": 7
    }
  ]
}